minagent/__init__.py
minagent/agent.py
minagent/prompt.py
minagent-0.1.1.dist-info/METADATA
minagent-0.1.1.dist-info/WHEEL
minagent-0.1.1.dist-info/licenses/LICENSE
minagent-0.1.1.dist-info/RECORD
