Metadata-Version: 2.4
Name: minagent
Version: 0.1.1
Summary: A wrapper on top of OpenAI chat completion and assistant API. It handles `tool_call`, `file_search` within the class.
Project-URL: Homepage, https://github.com/xuyangbocn/minagent
Project-URL: Issues, https://github.com/xuyangbocn/minagent/issues
Author-email: xuyangbo <xuyangbocn@gmail.com>
License-Expression: MIT
License-File: LICENSE
Classifier: Operating System :: OS Independent
Classifier: Programming Language :: Python :: 3
Requires-Python: >=3.8
Requires-Dist: openai
